README.md
setup.py
textflip/__init__.py
textflip/commandline.py
textflip/data.py
textflip/rotation.py
textflip/test_rotation.py
textflip.egg-info/PKG-INFO
textflip.egg-info/SOURCES.txt
textflip.egg-info/dependency_links.txt
textflip.egg-info/entry_points.txt
textflip.egg-info/requires.txt
textflip.egg-info/top_level.txt