Metadata-Version: 1.1
Name: textflip
Version: 0.3.4
Summary: Flip text by 180°
Home-page: https://github.com/L3viathan/textflip
Author: L3viathan
Author-email: git@l3vi.de
License: UNKNOWN
Platform: UNKNOWN
Classifier: Programming Language :: Python :: 3
Classifier: Operating System :: OS Independent
Classifier: Intended Audience :: Developers
